{
    "files": [
        {
            "title": "Edukasi Manfaat Tanaman Obat dan Pengolahannya dengan Metode CBIA",
            "pdf": "pdf/1215-2939-2-PB.pdf",
            "text": "text/1215-2939-2-PB.txt",
            "image": "images/1215-2939-2-PB.png"
        },
        {
            "title": "TUMBUHAN HERBAL SEBAGAI JAMU PENGOBATAN TRADISIONAL",
            "pdf": "pdf/124817-ID-none.pdf",
            "text": "text/124817-ID-none.txt",
            "image": "images/124817-ID-none.png"
        },
        {
            "title": "Jenis Tumbuhan yang Digunakan sebagai Obat Tradisional Di Daerah Eks-Karesidenan Surakarta",
            "pdf": "pdf/19672-61714-2-PB.pdf",
            "text": "text/19672-61714-2-PB.txt",
            "image": "images/19672-61714-2-PB.png"
        },
        {
            "title": "JENIS TANAMAN YANG DIGUNAKAN UNTUK OBAT TRADISIONAL DI KECAMATAN KLUET SELATAN",
            "pdf": "pdf/2974-6036-1-SM.pdf",
            "text": "text/2974-6036-1-SM.txt",
            "image": "images/2974-6036-1-SM.png"
        },
        {
            "title": "PEMANFAATAN TANAMAN OBAT (BIOFARMAKA)",
            "pdf": "pdf/3007-5860-1-SM.pdf",
            "text": "text/3007-5860-1-SM.txt",
            "image": "images/3007-5860-1-SM.png"
        },
        {
            "title": "PENGGUNAAN TANAMAN HERBAL UNTUK KESEHATAN",
            "pdf": "pdf/37-Article Text-66-1-10-20190525.pdf",
            "text": "text/37-Article Text-66-1-10-20190525.txt",
            "image": "images/37-Article Text-66-1-10-20190525.png"
        },
        {
            "title": "PEMANFAATAN JENIS TUMBUHAN OBAT TRADISIONAL DI DESA BATU HAMPARAN KABUPATEN ACEH TENGGARA",
            "pdf": "pdf/4039-8209-1-SM.pdf",
            "text": "text/4039-8209-1-SM.txt",
            "image": "images/4039-8209-1-SM.png"
        },
        {
            "title": "Pemanfaatan obat tradisional di Indonesia: distribusi dan faktor demografis yang berpengaruh",
            "pdf": "pdf/adiyasa-p130-138.pdf",
            "text": "text/adiyasa-p130-138.txt",
            "image": "images/adiyasa-p130-138.png"
        },
        {
            "title": "Buku Saku Tanaman Obat Keluarga (TOGA)",
            "pdf": "pdf/agropustaka.id_Buku-Saku-Tanaman-Obat-Keluarga-TOGA.pdf",
            "text": "text/agropustaka.id_Buku-Saku-Tanaman-Obat-Keluarga-TOGA.txt",
            "image": "images/agropustaka.id_Buku-Saku-Tanaman-Obat-Keluarga-TOGA.png"
        },
        {
            "title": "Budidaya Tanaman Obat Rempah",
            "pdf": "pdf/Budidaya-Tanaman-Obat-Rempah_Umsu-Press.pdf",
            "text": "text/Budidaya-Tanaman-Obat-Rempah_Umsu-Press.txt",
            "image": "images/Budidaya-Tanaman-Obat-Rempah_Umsu-Press.png"
        },
        {
            "title": "Rempah & Herba",
            "pdf": "pdf/E-book-Rempah-Herba-Luchman-HAkim-2016.pdf",
            "text": "text/E-book-Rempah-Herba-Luchman-HAkim-2016.txt",
            "image": "images/E-book-Rempah-Herba-Luchman-HAkim-2016.png"
        },
        {
            "title": "PEMANFAATAN TANAMAN HERBAL SEBAGAI OBAT TRADISIONAL",
            "pdf": "pdf/Jurnal+VILCO+upload.pdf",
            "text": "text/Jurnal+VILCO+upload.txt",
            "image": "images/Jurnal+VILCO+upload.png"
        }
    ]
}
